toupy/__init__.py
toupy/io/__init__.py
toupy/io/dataio.py
toupy/io/filesrw.py
toupy/io/h5chunk_shape_3D.py
toupy/registration/__init__.py
toupy/registration/registration.py
toupy/registration/shift.py
toupy/resolution/FSC.py
toupy/resolution/FSCtools.py
toupy/resolution/__init__.py
toupy/restoration/GUI_tracker.py
toupy/restoration/__init__.py
toupy/restoration/derivativetools.py
toupy/restoration/ramptools.py
toupy/restoration/roipoly.py
toupy/restoration/unwraptools.py
toupy/restoration/vorticestools.py
toupy/simulation/__init__.py
toupy/simulation/phantom_creator.py
toupy/tomo/__init__.py
toupy/tomo/iradon.py
toupy/tomo/radon.py
toupy/tomo/tomorecons.py
toupy/utils/FFT_utils.py
toupy/utils/__init__.py
toupy/utils/array_utils.py
toupy/utils/converter_utils.py
toupy/utils/fit_utils.py
toupy/utils/funcutils.py
toupy/utils/plot_utils.py
toupy-0.2.2.data/scripts/create_toupy_templates
toupy-0.2.2.data/scripts/file_comp
toupy-0.2.2.data/scripts/missing_recons
toupy-0.2.2.data/scripts/plot_projections
toupy-0.2.2.dist-info/LICENSE
toupy-0.2.2.dist-info/METADATA
toupy-0.2.2.dist-info/WHEEL
toupy-0.2.2.dist-info/top_level.txt
toupy-0.2.2.dist-info/RECORD
