Metadata-Version: 2.1
Name: toupy
Version: 0.2.2
Summary: Tomographic Utilities for Python
Home-page: https://github.com/jcesardasilva/toupy
Author: Julio Cesar da Silva
Author-email: julio-cesar.da-silva@neel.cnrs.fr
License: GPLv3 License
Project-URL: Bug Tracker, https://github.com/jcesardasilva/toupy/issues
Platform: UNKNOWN
Classifier: Programming Language :: Python :: 3
Classifier: License :: OSI Approved :: GNU General Public License v3 or later (GPLv3+)
Classifier: Topic :: Scientific/Engineering
Classifier: Topic :: Software Development
Classifier: Operating System :: Unix
Requires-Python: >=3.6
License-File: LICENSE
Requires-Dist: fabio (>=0.11.0)
Requires-Dist: h5py (>=3.1.0)
Requires-Dist: ipython (>=7.16.1)
Requires-Dist: joblib (>=1.0.1)
Requires-Dist: matplotlib (>=3.3.4)
Requires-Dist: numpy (>=1.16.5)
Requires-Dist: numexpr (>=2.6.9)
Requires-Dist: scipy (>=1.5.4)
Requires-Dist: PyFFTW (>=0.11.1)
Requires-Dist: pyopencl (>=2021.1.1)
Requires-Dist: scikit-image (>=0.17.2)
Requires-Dist: silx (>=0.9.0)
Requires-Dist: tqdm (>=4.61.2)
